[{"MedicalRecordId":1,"SurveyResponses":[],"Username":"miloskrickovic","Password":"12345678","ParentsName":"Milan","Gender":"Male","Email":"mikikriki@gmail.com","Jmbg":"1112221112221","PhoneNumber":"069-145-987","Adress":"Valentina Vodnika 14, Novi Sad","Biography":null,"Birthday":"1996-12-06T00:00:00","Name":"Milos","Surname":"Krickovic","Id":1},{"MedicalRecordId":2,"SurveyResponses":[],"Username":"jovankabroz","Password":"12345678","ParentsName":"NN","Gender":"Female","Email":"jovankabroz@gmail.com","Jmbg":"2221112221112","PhoneNumber":"064-155-417","Adress":"Nepoznata ulica bb, Novi Sad","Biography":null,"Birthday":"1990-11-07T00:00:00","Name":"Jovanka","Surname":"Broz","Id":2},{"MedicalRecordId":3,"SurveyResponses":[],"Username":"milicamicic","Password":"12345678","ParentsName":"Ilija","Gender":"Female","Email":"milicamicic@gmail.com","Jmbg":"2223332223332","PhoneNumber":"061-292-674","Adress":"Koste Racina bb, Novi Sad","Biography":null,"Birthday":"1963-06-07T00:00:00","Name":"Milica","Surname":"Micic","Id":3},{"MedicalRecordId":4,"SurveyResponses":[],"Username":"ivanivanovic","Password":"12345678","ParentsName":"Milan","Gender":"Male","Email":"ivanivanovic@gmail.com","Jmbg":"333222333222","PhoneNumber":"069-145-987","Adress":"Valentina Vodnika 14, Novi Sad","Biography":null,"Birthday":"1996-12-06T00:00:00","Name":"Ivan","Surname":"Ivanovic","Id":4},{"MedicalRecordId":5,"SurveyResponses":[],"Username":"stevicacvarkov","Password":"12345678","ParentsName":"Jovan","Gender":"Male","Email":"stevicacvarkov@gmail.com","Jmbg":"3334443334443","PhoneNumber":"064-155-417","Adress":"Nepoznata ulica bb, Novi Sad","Biography":null,"Birthday":"1990-11-07T00:00:00","Name":"Stevica","Surname":"Cvarkov","Id":5},{"MedicalRecordId":6,"SurveyResponses":[],"Username":"jagodamarkov","Password":"12345678","ParentsName":"Ilija","Gender":"Female","Email":"jagodamarkov@gmail.com","Jmbg":"4443334443334","PhoneNumber":"061-292-674","Adress":"Koste Racina bb, Novi Sad","Biography":null,"Birthday":"1963-06-07T00:00:00","Name":"Jagoda","Surname":"Markov","Id":6},{"MedicalRecordId":7,"SurveyResponses":[],"Username":"mikikriki","Password":"12345678","ParentsName":"Milan","Gender":"Male","Email":"mikikriki@gmail.com","Jmbg":"4445554445554","PhoneNumber":"069-145-987","Adress":"Valentina Vodnika 11, Novi Sad","Biography":null,"Birthday":"1996-12-06T00:00:00","Name":"Velinko","Surname":"Popara","Id":7},{"MedicalRecordId":8,"SurveyResponses":[],"Username":"visekruna","Password":"12345678","ParentsName":"NN","Gender":"Male","Email":"visekruna@gmail.com","Jmbg":"5554445554445","PhoneNumber":"064-155-417","Adress":"Nepoznata ulica bb, Novi Sad","Biography":null,"Birthday":"1990-11-07T00:00:00","Name":"Stevo","Surname":"Visekruna","Id":8},{"MedicalRecordId":9,"SurveyResponses":[],"Username":"loncar","Password":"12345678","ParentsName":"Ilija","Gender":"Male","Email":"loncar@gmail.com","Jmbg":"6665556665556","PhoneNumber":"061-292-674","Adress":"Koste Racina bb, Novi Sad","Biography":null,"Birthday":"1963-06-07T00:00:00","Name":"Ninoslav","Surname":"Loncar","Id":9},{"MedicalRecordId":10,"SurveyResponses":[],"Username":"stupar","Password":"12345678","ParentsName":"Ilija","Gender":"Male","Email":"stupar@gmail.com","Jmbg":"8889998889998","PhoneNumber":"061-292-674","Adress":"Koste Racina bb, Novi Sad","Biography":null,"Birthday":"1963-06-07T00:00:00","Name":"Milan","Surname":"Stupar","Id":10}]